setup.py
affect/__init__.py
affect/admin.py
affect/middleware.py
affect/models.py
affect/utils.py
affect/views.py
affect/migrations/0001_initial.py
affect/migrations/__init__.py
django_affect.egg-info/PKG-INFO
django_affect.egg-info/SOURCES.txt
django_affect.egg-info/dependency_links.txt
django_affect.egg-info/requires.txt
django_affect.egg-info/top_level.txt