Metadata-Version: 1.1
Name: django-affect
Version: 1.0.0
Summary: Request flagging engine inspired by django-waffle
Home-page: https://github.com/ConsumerAffairs/django-affect
Author: Jeremy Sattefield
Author-email: jsatterfield@consumeraffairs.com
License: UNKNOWN
Platform: UNKNOWN
Classifier: Development Status :: 5 - Production/Stable
Classifier: Environment :: Web Environment
Classifier: Framework :: Django
Classifier: Intended Audience :: Developers
Classifier: Operating System :: OS Independent
Classifier: Programming Language :: Python
Classifier: Topic :: Internet :: WWW/HTTP :: Site Management
